jarviceclient/JarviceAPI.py
jarviceclient/__init__.py
jarviceclient/exceptions.py
jarviceclient/utils.py
jarviceclient3-1.0.7.data/scripts/jarvice_cli
jarviceclient3-1.0.7.dist-info/LICENSE.md
jarviceclient3-1.0.7.dist-info/METADATA
jarviceclient3-1.0.7.dist-info/WHEEL
jarviceclient3-1.0.7.dist-info/top_level.txt
jarviceclient3-1.0.7.dist-info/RECORD
