Metadata-Version: 2.1
Name: jarviceclient3
Version: 1.0.7
Summary: Jarvice API Python 3 Client for Nimbix, Inc.
Home-page: http://www.nimbix.net
Maintainer: Nimbix
Maintainer-email: support@nimbix.net
License: LICENSE.md
Platform: UNKNOWN
Classifier: Development Status :: 5 - Production/Stable
Classifier: Environment :: Console
Classifier: Intended Audience :: End Users/Desktop
Classifier: Intended Audience :: Developers
Classifier: Intended Audience :: System Administrators
Classifier: Intended Audience :: Science/Research
Classifier: Operating System :: MacOS :: MacOS X
Classifier: Operating System :: Microsoft :: Windows
Classifier: Operating System :: POSIX
Classifier: Programming Language :: Python
Classifier: Topic :: System :: Distributed Computing
Classifier: Topic :: Software Development :: Libraries :: Python Modules
Classifier: Topic :: Utilities
Classifier: License :: OSI Approved :: BSD License
Requires-Dist: ecdsa
Requires-Dist: paramiko
Requires-Dist: pycryptodome
Requires-Dist: requests
Requires-Dist: simplejson
